data.txt
dieai-1.0.0.dist-info/licenses/LICENSE
dieai_knowledge/__init__.py
dieai_knowledge/chatbot.py
dieai_knowledge/client.py
dieai_knowledge/knowledge_base.py
dieai_knowledge/math_solver.py
dieai_knowledge/science_facts.py
dieai_knowledge/unit_converter.py
dieai-1.0.0.dist-info/METADATA
dieai-1.0.0.dist-info/WHEEL
dieai-1.0.0.dist-info/top_level.txt
dieai-1.0.0.dist-info/RECORD
