Metadata-Version: 2.4
Name: dieai
Version: 1.0.0
Summary: AI library similar to OpenAI for building chatbots and intelligent applications
Home-page: https://github.com/dieai/dieai
Author: DieAI Team
Author-email: DieAI Team <info@dieai.com>
License: MIT
Project-URL: Homepage, https://github.com/dieai/dieai-knowledge
Project-URL: Bug Reports, https://github.com/dieai/dieai-knowledge/issues
Project-URL: Source, https://github.com/dieai/dieai-knowledge
Project-URL: Documentation, https://github.com/dieai/dieai-knowledge/wiki
Keywords: mathematics,science,physics,chemistry,biology,education,knowledge,ai
Classifier: Development Status :: 4 - Beta
Classifier: Intended Audience :: Education
Classifier: Intended Audience :: Science/Research
Classifier: License :: OSI Approved :: MIT License
Classifier: Operating System :: OS Independent
Classifier: Programming Language :: Python :: 3
Classifier: Programming Language :: Python :: 3.8
Classifier: Programming Language :: Python :: 3.9
Classifier: Programming Language :: Python :: 3.10
Classifier: Programming Language :: Python :: 3.11
Classifier: Programming Language :: Python :: 3.12
Classifier: Topic :: Scientific/Engineering
Classifier: Topic :: Scientific/Engineering :: Mathematics
Classifier: Topic :: Scientific/Engineering :: Physics
Classifier: Topic :: Scientific/Engineering :: Chemistry
Classifier: Topic :: Education
Requires-Python: >=3.8
License-File: LICENSE
Dynamic: author
Dynamic: home-page
Dynamic: license-file
Dynamic: requires-python
